{
    "scheme_name": "HDFC Gold ETF Fund of Fund Direct Plan Growth",
    "category": "Commodities",
    "sub_category": "Gold",
    "riskometer": "Moderately High Riskometer",
    "launch_date": "01-Jan-2013",
    "lock_in": "No lock-in period",
    "benchmark": "Domestic Price of Gold",
    "benchmark_name": "Domestic Price of Gold",
    "description": "The Scheme seeks to generate capital appreciation by investing in units of HDFC Gold Exchange Traded Fund.",
    "nav": 48.9072,
    "nav_date": "26-May-2026",
    "expense_ratio": "0.21",
    "aum": 11464.3532,
    "min_sip": 100,
    "min_lumpsum": 100,
    "exit_load": "Exit load of 1%, if redeemed within 15 days.",
    "managers": [
        {
            "name": "Arun Agarwal",
            "experience": "Prior to joining HDFC Asset Management Company Limited, he has worked with SBI Funds Management Pvt. Ltd., ICICI Bank Limited, UTI Asset Management Pvt. Ltd.",
            "education": "Mr. Agarwal is a B.Com. and Chartered Accountant"
        },
        {
            "name": "Nandita Menezes",
            "experience": "Prior to joining HDFC AMC, she was associated with S.V. Ghatalia & Associates LLP.",
            "education": "CA (ICAI, INDIA), B.Com (University of Mumbai)"
        }
    ],
    "holdings": [
        {
            "company_name": "HDFC Gold ETF",
            "sector": "",
            "percentage": 100.1
        }
    ]
}